webship/__init__.py
webship/tasks.py
webship-0.1.2.dist-info/entry_points.txt
webship-0.1.2.dist-info/WHEEL
webship-0.1.2.dist-info/METADATA
webship-0.1.2.dist-info/RECORD
