Metadata-Version: 2.1
Name: webship
Version: 0.1.2
Summary: Tools to deploy python web application
Home-page: https://github.com/xoxzo/webship
License: MIT
Author: kamal
Author-email: kamal@xoxzo.com
Requires-Python: >=3.8,<4.0
Classifier: License :: OSI Approved :: MIT License
Classifier: Programming Language :: Python :: 3
Classifier: Programming Language :: Python :: 3.8
Classifier: Programming Language :: Python :: 3.9
Requires-Dist: fabric2 (>=2.5.0,<3.0.0)
Project-URL: Repository, https://github.com/xoxzo/webship
